README.md
setup.py
mdc_tools/__init__.py
mdc_tools/comm.py
mdc_tools/grid_search.py
mdc_tools/iotools.py
mdc_tools/jupyter_imports.py
mdc_tools/logger.py
mdc_tools/math_tools.py
mdc_tools/post_process.py
mdc_tools/pytorch_tools.py
mdc_tools/reid.py
mdc_tools/timer.py
mdc_tools/visualize.py
mdc_tools.egg-info/PKG-INFO
mdc_tools.egg-info/SOURCES.txt
mdc_tools.egg-info/dependency_links.txt
mdc_tools.egg-info/requires.txt
mdc_tools.egg-info/top_level.txt
scripts/imginfo
scripts/mdctools
scripts/mprun
scripts/smail
scripts/tmux_sched
scripts/vpdb