Metadata-Version: 1.0
Name: mdc-tools
Version: 1.4.4
Summary: Personal tools
Home-page: https://github.com/silverbulletmdc/mdc_tools
Author: Dechao Meng
Author-email: dechao.meng@vipl.ict.ac.cn
License: UNKNOWN
Platform: UNKNOWN
